metaheuristic_algorithms/base_algorithm.py
metaheuristic_algorithms/command_line.py
metaheuristic_algorithms/firefly_algorithm.py
metaheuristic_algorithms/genetic_algorithm.py
metaheuristic_algorithms/harmony_search.py
metaheuristic_algorithms/simplified_particle_swarm_optimization.py
metaheuristic_algorithms/simulated_annealing.py
metaheuristic_algorithms/version.py
metaheuristic_algorithms/function_wrappers/abstract_wrapper.py
metaheuristic_algorithms/function_wrappers/easom_function_wrapper.py
metaheuristic_algorithms/function_wrappers/michaelwicz_function_wrapper.py
metaheuristic_algorithms/function_wrappers/nonsmooth_multipeak_function_wrapper.py
metaheuristic_algorithms/function_wrappers/rosenbrook_function_wrapper.py
metaheuristic_algorithms_python-0.1.6.dist-info/DESCRIPTION.rst
metaheuristic_algorithms_python-0.1.6.dist-info/entry_points.txt
metaheuristic_algorithms_python-0.1.6.dist-info/METADATA
metaheuristic_algorithms_python-0.1.6.dist-info/metadata.json
metaheuristic_algorithms_python-0.1.6.dist-info/RECORD
metaheuristic_algorithms_python-0.1.6.dist-info/top_level.txt
metaheuristic_algorithms_python-0.1.6.dist-info/WHEEL
tests/metaheuristic_algorithms/test_firefly_algorithm.py
tests/metaheuristic_algorithms/test_genetic_algorithm.py
tests/metaheuristic_algorithms/test_harmony_search.py
tests/metaheuristic_algorithms/test_simplified_particle_swarm_optimization.py
tests/metaheuristic_algorithms/test_simulated_annealing.py
