Metadata-Version: 2.0
Name: metaheuristic-algorithms-python
Version: 0.1.6
Summary: Various metaheuristic algorithms implemented in Python
Home-page: https://github.com/tadatoshi/metaheuristic_algorithms_python
Author: Tadatoshi Takahashi
Author-email: tadatoshi@gmail.com
License: MIT
Keywords: control optimization engineering
Platform: UNKNOWN
Classifier: Development Status :: 3 - Alpha
Classifier: Intended Audience :: Developers
Classifier: Topic :: Scientific/Engineering
Classifier: License :: OSI Approved :: MIT License
Classifier: Programming Language :: Python :: 3.4
Classifier: Programming Language :: Python :: 3.5
